mcp_ola_maps/__init__.py
mcp_ola_maps/main.py
mcp_ola_maps/mcp_env.py
mcp_ola_maps/mcp_server.py
ola_maps_mcp_server-0.2.4.dist-info/METADATA
ola_maps_mcp_server-0.2.4.dist-info/WHEEL
ola_maps_mcp_server-0.2.4.dist-info/entry_points.txt
ola_maps_mcp_server-0.2.4.dist-info/licenses/LICENSE
ola_maps_mcp_server-0.2.4.dist-info/RECORD
