Metadata-Version: 2.4
Name: ola-maps-mcp-server
Version: 0.2.4
Summary: MCP server for Ola Maps
Author: Ola Maps Team
Maintainer-email: Pankaj Verma <pankaj.verma1@olakrutrim.com>
License-Expression: MIT
License-File: LICENSE
Keywords: Maps,Ola,llm,mcp
Requires-Python: >=3.10
Requires-Dist: httpx>=0.28.1
Requires-Dist: mcp[cli]>=1.6.0
Requires-Dist: polyline>=2.0.0
